{
    "_emoji": "se",
    "_name": "Svenska (Swedish)",
    "embed_warn": "[VARNING] Botten har inte beh칬righet att b칛dda in l칛nkar.",
    "no_start_that": "Tyv칛rr, {{user}}, men den anv칛ndaren har inte startat 칛n.",
    "no_start": "Var sn칛ll och skapa ditt konto genom att anv칛nda `{{prefix}}stats` kommandot.",
    "started_acct": "{{user}}, skapade konto utan problem.",
    "cant_start_week": "Tyv칛rr, {{user}}, men ditt Discord konto m친ste vara en vecka gammal f칬r att kunna spela.",
    "your_bal": "Ditt :credit_card: Saldo 칛r **{{amount}}**.",
    "their_bal": "Deras :credit_card: Saldo 칛r **{{amount}}**.",
    "series_locked": "Den h칛r serien utvecklas fortfarande.",
    "cant_affort": "Har inte r친d med det!",
    "series_bought": "K칬pte {{item}} Paket.",
    "series_bought_a": "K칬pte ett {{item}} Paket.",
    "item_found": "Hittade 1 artikel.",
    "items_found": "Hittade {{amount}} artiklar.",
    "found_specific": "Var sn칛ll och var mer specifik.",
    "no_card_id_found": "Tyv칛rr, {{user}}, men inget kort har det ID:t.",
    "no_card_exist_found": "Tyv칛rr, {{user}}, men det kortet finns inte.",
    "no_series_id_found": "Tyv칛rr, {{user}}, men inga serier har det ID:t.",
    "no_series_exist_found": "Tyv칛rr, {{user}}, men den serien finns inte.",
    "no_badge_exist_found": "Tyv칛rr, {{user}}, men det emblemet finns inte.",
    "no_rarity_found": "Tyv칛rr, {{user}}, men den s칛llsyntheten finns inte. Anv칛nd snabbskriftliga namn.",
    "specify_card_pack": "Var sn칛ll och ange ett kortpaket, {{user}}.",
    "specify_card": "Var sn칛ll och ange ett kort, {{user}}.",
    "specify_badge": "Var sn칛ll och ange ett emblem, {{user}}.",
    "c": "Vanlig",
    "uc": "Ovanlig",
    "r": "S칛llsynt",
    "sr": "V칛ldigt S칛llsynt",
    "need_embed": "Jag m친ste ha \"B칛dda in L칛nkar\" beh칬righet f칬r det h칛r kommandot!",
    "large_bet": "Alltf칬r stor satsning!",
    "invalid_bet": "Ogiltig satsning!",
    "specify_bet": "Var sn칛ll och ange en satsning.",
    "slots_no_match": "Ingen matchning! F칬rs칬k igen!",
    "slots_all_match": "Spunna alla **{{slot}}**, vann",
    "slots_two_match": "Spunnit 2 **{{slot}}**, vann",
    "insufficient_currency": "Tyv칛rr, {{user}}, men du har inte tillr칛ckligt med :dollar: f칬r att forts칛tta.",
    "opened_pack": "{{user}} 칐ppnade En {{item}} Paket och fick...",
    "pre_generation": "Genererar bild, var v칛nlig och v칛nta. Om det h칛r misslyckas att generera, s친 har dina kort blivit sparade f칬re genereringen.",
    "image_failed": "Bildf칬rfr친gan misslyckades",
    "send_to_pm": "Skickade hela hj칛lpen till dina Privat Meddelanden!",
    "help_more_info": "`{{prefix}}help [command]` f칬r mer information.",
    "usage": "Anv칛ndning",
    "description": "Beskrivning",
    "aliases": "Alias",
    "time_taken": "Tid tagen: {{seconds}} Sekunder",
    "msg_delay": "Meddelande Tidsst칛mpel F칬rdr칬jning: {{seconds}} Sekunder",
    "error": "Ett problem uppstod, problemet har blivit rapporterad till den officiella servern. Rapport koden 칛r `{{code}}`.",
    "pong": "Pong",
    "nomem_error": "Bildprocessorn fick slut p친 minne!",
    "query_error": "V친r s칬kparser hade ett fel med din f칬rfr친gan, f칬rs칬k att anv칛nda en annan fr친ga.",
    "command_serverinvite": "Du kan g친 med i servern med den h칛r l칛nken:",
    "command_invite": "Bjud in botten med den h칛r l칛nken:",
    "command_bug": "Du kan rapportera buggar med den h칛r l칛nken:",
    "cardguess_stop": "Avslutade minispelet.",
    "await_timeout": "Du misslyckades med att svara inom 30 sekunder! Var sn칛ll och f칬rs칬k igen!",
    "await_overwritten": "F칬rfr친gan 칬verskrevs p친 n친got s칛tt. Var sn칛ll och f칬rs칬k igen!",
    "cardguess_start_1": "Gissa vilket kort det 칛r! Du har 30 sekunder",
    "cardguess_start_2": "Skriv `cancel` n칛r som helst f칬r att avsluta.",
    "cardguess_fail": "Misslyckades att gissa `{{item}}` korrekt! F칬rs칬k igen senare!",
    "cardguess_success": "Du gissade r칛tt!",
    "cardguess_success_guess": "Jag antar att du menade `{{item}}`. Om det 칛r s친, gissade du r칛tt!",
    "cardguess_wrong": "Fel!",
    "invalid_arg": "Ogiltigt argument!",
    "invalid_locale": "Ogiltigt spr친k!",
    "invalid_settings_perms": "Du m친ste ha `{{role}}` rollen f칬r att 칛ndra server inst칛llningar!",
    "invalid_hex": "Tyv칛rr, {{user}}, men det 칛r inte en giltig HEX f칛rg.",
    "invalid_bool": "Tyv칛rr, {{user}}, men jag vet inte vad du vill g칬ra. Anv칛nd ord som `yes` eller `no`.",
    "no_use_pms": "Du kan inte anv칛nda det kommandot i Privat Meddelanden!",
    "not_setting": "Det 칛r ingen inst칛llning, {{user}}.",
    "prefix_setting": "Prefix satt till `{{prefix}}`.",
    "locale_setting": "Spr친k satt till `{{locale}}`.",
    "_dollar": "游눳",
    "no_album_id_found": "Urs칛kta, {{user}}, men inget album har det ID.",
    "specify_album_id": "Var sn칛ll och specificera ett album ID, {{user}}.",
    "l": "Begr칛nsad",
    "need_embed_emojis": "Jag m친ste ha Inb칛ddnings L칛nk och Andv칛nd Externa Emojis tillst친nd f칬r det h칛r kommandot!",
    "help_extra.search_card": "S칬ker korterbjudanden med det ID",
    "help_extra.search_rarity": "S칬ker korterbjudanden med den s칛llsyntheten",
    "help_extra.search_series": "S칬ker kort och kortpakets erbjudanden med den seriens ID",
    "help_extra.buy_series": "K칬per kortpaket med det ID",
    "help_extra.card_card_id": "Hittar ett kort med det ID",
    "help_extra.openpack_card_pack": "칐ppnar kortpaket med det ID",
    "help_extra.fusecards_series_id": "Sl친r samman kort av den serien med det ID",
    "help_extra.modifiers": "Modifierare",
    "help_extra.settings": "Inst칛llningar",
    "help_extra.note": "Notera",
    "help_extra.mod_card_id": "KORT_ID",
    "help_extra.mod_rarity": "S츿LLSYNTHET",
    "help_extra.mod_series": "SERIER",
    "help_extra.mod_series_id": "SERIER_ID",
    "help_extra.setting_hex": "HEX F칛rg",
    "help_extra.setting_base_name": "Baner Bas Namn",
    "help_extra.setting_design_name": "Baner Design Namn",
    "help_extra.setting_bool": "Ja/Nej",
    "help_extra.setting_string": "Str칛ng",
    "help_extra.setting_note_locale_list": "`{{prefix}} locale list` f칬r att lista platser tillg칛ngliga.",
    "help_desc.album": "Visar information om ett album.",
    "help_desc.albums": "Visar alla album",
    "help_desc.badge": "Visar information om en bricka.",
    "no_card": "Du har inte det kortet!",
    "no_available_albums": "Inget album beh칬ver det kortet.",
    "album_which": "Skriv numret av albumet du vill matcha detta kort med. Tillg칛ngliga album: {{albums}} Eller skriv `c` f칬r att avbryta.",
    "help_desc.badges": "Visar alla brickor",
    "help_desc.balance": "F친 din egna balans (eller n친gon annans)",
    "time": "{{days}} Dagar {{hours}} Timmar {{minutes}} Minuter {{seconds}} Sekunder",
    "shop": "Butik",
    "minigames": "Minispel",
    "album_add_piece": "{{user}} lade till en bit till albumet #{{album}}!",
    "operation_canceled": "Funktionen avbruten",
    "help_desc.boexecute": "Genomf칬r ett k칬p erbjudande p친 den globala marknaden",
    "help_desc.bug": "F친 en l칛nk till fels칬karen.",
    "help_desc.buypack": "K칬p ett paket.",
    "help_desc.card": "Visar information om ett kort.",
    "help_desc.cardguess": "Gissa kort f칬r :dollar:.",
    "help_desc.cards": "Visar en lista av kort",
    "help_desc.cban": "Bannar n친gon fr친n klubben.",
    "help_desc.cbanlist": "Visa klubb bans",
    "help_desc.ccreate": "Skapa en klubb",
    "help_desc.ceditdesc": "츿ndrar beskrivningen av en klubb",
    "help_desc.ceditname": "Byter namn p친 en klubb",
    "help_desc.cgiveowner": "칐verf칬r klubb 칛garskapet till n친gon",
    "help_desc.cinv": "Bjud in n친gon till en klubb.",
    "help_desc.cinvlist": "Visa klubb inbjudningar.",
    "help_desc.cjoin": "G친 med i en klubb",
    "help_desc.ckick": "Sparkar n친gon fr친n en klubb.",
    "help_desc.cleave": "L칛mna en klubb, g칬r du detta som 칛gare f칬rsvinner klubben",
    "help_desc.club": "Se en klubb",
    "help_desc.cmembers": "Se medlemmar i klubben.",
    "help_desc.crank": "Byter en rank av en person i klubben.",
    "help_desc.crinv": "Tar bort en inbjudan fr친n en klubb.",
    "help_desc.csetting": "츿ndra eller titta p친 inst칛llningar i klubben.",
    "help_desc.donate": "Donera n친gon :dollar:.",
    "help_desc.help": "Visar hj칛lp meddelande",
    "help_desc.invite": "F친 en inbjudnings l칛nk till boten",
    "help_desc.openpack": "칐ppnar ett paket.",
    "help_desc.daily": "Ta emot daglig :dollar:.",
    "help_desc.inv": "F친 ditt egna inventory (eller n친gon annans)",
    "help_desc.ping": "Pong!!",
    "help_desc.qget": "F친 en quest.",
    "help_desc.quest": "Se din nuvarande quest.",
    "help_desc.series": "Visar en lista av serier",
    "help_desc.serverinvite": "F친 en inbjudnings l칛nk till den officiella servern.",
    "help_desc.setting": "츿ndra eller se dina inst칛llningar.",
    "help_desc.slots": "G칬r slots f칬r :dollar:.",
    "help_desc.ssetting": "츿ndra eller se dina server inst칛llningar.",
    "help_desc.stats": "F친 din egen statistik (eller n친gon annans)",
    "help_desc.taccept": "Accepterar en utbytes f칬rfr친gan.",
    "help_desc.tadditem": "L칛gger till ett f칬rem친l till utbytet.",
    "help_desc.tdeny": "Avb칬jer eller stoppar ett utbyte.",
    "help_desc.bolist": "Visar en lista av alla k칬p erbjudanden",
    "help_desc.bosearch": "S칬ker f칬r ett f칬rem친l p친 k칬p erbjudanden.",
    "help_desc.cardtoalbum": "G칬r ett kort till en del av albumet.",
    "help_desc.ccode": "St칛ller in bannern som koden som genereras av [banner editor](http://discord.cards/banner-edit/).",
    "help_desc.cunban": "Tar bort en ban fr친n n친gon i en klubb.",
    "help_desc.fusecards": "S칛krar alla kort fr친n en serie till ett m칛rke.",
    "help_desc.gift": "S칛nk n친gon en sak",
    "help_desc.myoffers": "Visar en lista 칬ver dina aktuella erbjudanden",
    "help_desc.oinfo": "F친 erbjudande information",
    "help_desc.ostop": "Stoppar ett erbjudande",
    "help_desc.pbadges": "F친 dina medaljer (eller n친gon annans)",
    "help_desc.pclubs": "F친 dina klubbar (eller n친gon annans)",
    "help_desc.pong": "Ping!",
    "help_desc.qcheck": "Utf칬r din str칛van efter bel칬ningar.",
    "help_desc.soexecute": "Verkst칛ller ett f칬rs칛ljningsbud p친 den globala marknaden",
    "help_desc.soffer": "S칛tter ett s칛ljbud p친 den globala marknaden",
    "help_desc.solist": "Visar en lista 칬ver alla f칬rs칛ljningserbjudanden",
    "help_desc.sosearch": "S칬ker efter ett f칬rem친l p친 f칬rs칛ljnings erbjudanden.",
    "help_desc.boffer": "L칛gger ett k칬p erbjudande p친 den globala marknaden",
    "help_desc.tok": "V칛xlar med att acceptera den aktuella handeln.",
    "help_desc.trade": "Visar nuvarande handelsstatus.",
    "help_desc.tremoveitem": "Tar bort ett f칬rem친l fr친n utbytet.",
    "help_desc.tsetmoney": "St칛ller in hur mycket :dollar: du erbjuder.",
    "help_desc.tstart": "Starta en handelsf칬rfr친gan med en person",
    "ping": "Ping",
    "request_bad_gateway": "Den h칛r f칬rfr친gan tog f칬r l친ng tid, f칬rs칬k igen senare!",
    "user_locale_setting": "Anv칛ndaradressen satt till `{{locale}}`.",
    "locale_unset": "Inaktivera ditt spr친k. Din ort anv칛nder nu automatiskt den inst칛llda servern.",
    "unset_locale": "Inaktivera ditt spr친k.",
    "adminrole_setting": "Admin rollen satt till`{{role}}`.",
    "displaycolor_setting": "Visningsf칛rg inst칛lld p친 {{color}}.",
    "prefix": "Prefix:",
    "locale": "Spr친k:",
    "adminrole": "Admin Roll:",
    "displaycolor": "Visnings F칛rg:",
    "trades": "Utbyten:",
    "notifs": "Meddelanden:",
    "notifs_on": "Meddelanden 칛r nu p친.",
    "notifs_off": "Meddelanden 칛r nu av.",
    "trades_on": "Utbyten 칛r nu p친.",
    "trades_off": "Utbyten 칛r nu av.",
    "no_club": "Kan inte hitta den klubben!",
    "club_specify_user": "Sn칛lla specificera en anv칛ndare.",
    "cant_ban": "Du kan inte bannlysa en {{rank}} som en {{otherrank}}!",
    "cant_kick": "Du kan inte sparka en {{rank}} som en {{otherrank}}!",
    "club_not_admin": "Du 칛r inte en admin av denna klubb!",
    "club_not_owner": "Du 칛r inte 칛gare av denna klubb!",
    "club_ban": "Bannlyste {{user}} fr친n klubben.",
    "club_notif_ban": "Klubb {{rank}} {{user}} bannlyste dig fr친n klubben {{club}}.",
    "club_notif_rename": "{{user}} Bytte namn p친 klubben fr친n {{oldname}} till {{club}}.",
    "club_notif_ownership": "{{user}} gjorde dig till 칛gare av klubben {{club}}.",
    "club_notif_kick": "Klubb {{rank}} {{user}} sparkade dig fr친n klubben {{club}}.",
    "club_notif_disband": "{{user}} uppl칬ste klubben {{club}}.",
    "club_notif_rank": "{{user}} 칛ndrade din rank till {{rank}} i klubben {{club}}.",
    "not_in_club": "Du 칛r inte i denna klubben!",
    "club_specify_name": "Sn칛lla specificera ett namn.",
    "club_specify_code": "Sn칛lla specificera en kod, {{user}}.",
    "invalid_encoding": "Ogiltig kodning!",
    "club_header_bans": "{{club}}'s Bannlysningar",
    "club_header_invites": "{{club}}'s Inbjudningar",
    "club_header_members": "{{club}}'s Medlemmar.",
    "set_banner": "S칛tt en baner.",
    "invalid_format": "Formatet 칛r ogiltigt!",
    "club_name_limit": "F칬rl친t, {{user}}, men klubb namn kan inte vara mer 칛n 32 symboler l친nga.",
    "club_max_limit": "F칬rl친t, {{user}}, men du n친dde en gr칛ns p친 5 klubbar.",
    "club_name_exists": "F칬rl친t, {{user}}, men den klubben finns redan.",
    "club_create": "Skapade klubben!",
    "club_set_desc": "S칛tter klubbens beskrivning.",
    "club_set_name": "츿ndrar klubbens namn.",
    "user_not_in_club": "Den anv칛ndaren 칛r inte i denna klubben!",
    "club_gave_ownership": "Gav 칛garskap till {{user}}.",
    "user_in_club": "Den anv칛ndaren 칛r i klubben!",
    "user_already_invited": "Den anv칛ndaren 칛r redan inbjuden!",
    "user_not_invited": "Den anv칛ndaren 칛r inte inbjuden!",
    "club_invited": "Bj칬d in {{user}} till klubben. Skriv `{{prefix}}cjoin {{club}}` f칬r att g친 med i klubben!",
    "club_join": "Gick med i klubben.",
    "club_join_banned": "Du 칛r bannlyst fr친n denna klubben, fr친ga en admin till att ta bort din bannlysning."
}
